centrip_book.py
centrip_book-1.1.13.dist-info/METADATA
centrip_book-1.1.13.dist-info/WHEEL
centrip_book-1.1.13.dist-info/entry_points.txt
centrip_book-1.1.13.dist-info/top_level.txt
centrip_book-1.1.13.dist-info/RECORD
