Metadata-Version: 2.4
Name: centrip-book
Version: 1.1.13
Summary: A command bookmarking tool for your terminal.
Author: Centrip Studios
Requires-Python: >=3.6
Dynamic: author
Dynamic: description
Dynamic: description-content-type
Dynamic: requires-python
Dynamic: summary
